{"Similar": {"Info": [{"Name": "Muse", "Type": "music"}], "Results": [{"Name": "Placebo", "Type": "music"}, {"Name": "The Killers", "Type": "music"}, {"Name": "Red Hot Chili Peppers", "Type": "music"}, {"Name": "Franz Ferdinand", "Type": "music"}, {"Name": "Radiohead", "Type": "music"}, {"Name": "The White Stripes", "Type": "music"}, {"Name": "Coldplay", "Type": "music"}, {"Name": "Snow Patrol", "Type": "music"}, {"Name": "Kings Of Leon", "Type": "music"}, {"Name": "Arctic Monkeys", "Type": "music"}, {"Name": "Foo Fighters", "Type": "music"}, {"Name": "Gorillaz", "Type": "music"}, {"Name": "System Of A Down", "Type": "music"}, {"Name": "Nirvana", "Type": "music"}, {"Name": "30 Seconds To Mars", "Type": "music"}, {"Name": "The Offspring", "Type": "music"}, {"Name": "Oasis", "Type": "music"}, {"Name": "Bloc Party", "Type": "music"}, {"Name": "Editors", "Type": "music"}, {"Name": "Green Day", "Type": "music"}]}}